sophios/__init__.py
sophios/_version.py
sophios/ast.py
sophios/cli.py
sophios/compiler.py
sophios/config_basic.json
sophios/cwl_subinterpreter.py
sophios/inference.py
sophios/inlineing.py
sophios/input_output.py
sophios/main.py
sophios/plugins.py
sophios/post_compile.py
sophios/py.typed
sophios/python_cwl_adapter.py
sophios/run_local.py
sophios/utils.py
sophios/utils_cwl.py
sophios/utils_graphs.py
sophios/utils_yaml.py
sophios/wic_types.py
sophios/api/__init__.py
sophios/api/_types.py
sophios/api/pythonapi.py
sophios/api/http/__init__.py
sophios/api/http/restapi.py
sophios/api/utils/__init__.py
sophios/api/utils/converter.py
sophios/api/utils/input_object_schema.json
sophios/api/utils/wfb_util.py
sophios/api/utils/ict/__init__.py
sophios/api/utils/ict/ict_spec/__init__.py
sophios/api/utils/ict/ict_spec/cast.py
sophios/api/utils/ict/ict_spec/model.py
sophios/api/utils/ict/ict_spec/hardware/__init__.py
sophios/api/utils/ict/ict_spec/hardware/objects.py
sophios/api/utils/ict/ict_spec/io/__init__.py
sophios/api/utils/ict/ict_spec/io/objects.py
sophios/api/utils/ict/ict_spec/metadata/__init__.py
sophios/api/utils/ict/ict_spec/metadata/objects.py
sophios/api/utils/ict/ict_spec/tools/__init__.py
sophios/api/utils/ict/ict_spec/tools/cwl_ict.py
sophios/api/utils/ict/ict_spec/ui/__init__.py
sophios/api/utils/ict/ict_spec/ui/objects.py
sophios/cwl_adapters/ambiguous.cwl
sophios/cwl_adapters/append.cwl
sophios/cwl_adapters/array_float.cwl
sophios/cwl_adapters/array_indices.cwl
sophios/cwl_adapters/array_int.cwl
sophios/cwl_adapters/cat.cwl
sophios/cwl_adapters/check_linear_fit.cwl
sophios/cwl_adapters/dup.cwl
sophios/cwl_adapters/echo.cwl
sophios/cwl_adapters/echo_3.cwl
sophios/cwl_adapters/fail.cwl
sophios/cwl_adapters/filter_array.cwl
sophios/cwl_adapters/glob_pattern.cwl
sophios/cwl_adapters/identity.cwl
sophios/cwl_adapters/nvidia_smi.cwl
sophios/cwl_adapters/random_subset_rows.cwl
sophios/cwl_adapters/scatter_plot.cwl
sophios/cwl_adapters/subdirectory.cwl
sophios-0.3.1.dist-info/LICENSE
sophios-0.3.1.dist-info/METADATA
sophios-0.3.1.dist-info/WHEEL
sophios-0.3.1.dist-info/entry_points.txt
sophios-0.3.1.dist-info/top_level.txt
sophios-0.3.1.dist-info/RECORD
