Metadata-Version: 2.2
Name: sophios
Version: 0.3.1
Summary: DSL for inferring the edges of a CWL workflow DAG
Author-email: Jake Fennick <jake.fennick@axleinfo.com>
Project-URL: Homepage, https://github.com/PolusAI/workflow-inference-compiler
Project-URL: Bug Tracker, https://github.com/PolusAI/workflow-inference-compiler/issues
Classifier: Programming Language :: Python :: 3
Classifier: License :: OSI Approved :: MIT License
Classifier: Operating System :: OS Independent
Requires-Python: >=3.8
License-File: LICENSE
Requires-Dist: cwltool
Requires-Dist: graphviz
Requires-Dist: jsonschema
Requires-Dist: pyyaml
Requires-Dist: requests
Requires-Dist: mergedeep
Requires-Dist: networkx
Requires-Dist: cwl-utils>=0.32
Requires-Dist: typeguard
Requires-Dist: pydantic>=2.6
Requires-Dist: pydantic-settings
Requires-Dist: pydantic[email]
Requires-Dist: docker
Requires-Dist: podman
Requires-Dist: toil[cwl]
Requires-Dist: fastapi
Requires-Dist: python-jose
Requires-Dist: uvicorn
Requires-Dist: referencing
Provides-Extra: test
Requires-Dist: pre-commit; extra == "test"
Requires-Dist: py; extra == "test"
Requires-Dist: pytest; extra == "test"
Requires-Dist: pytest-cov; extra == "test"
Requires-Dist: pytest-parallel; extra == "test"
Requires-Dist: coverage; extra == "test"
Requires-Dist: mypy; extra == "test"
Requires-Dist: numpy; extra == "test"
Requires-Dist: scipy; extra == "test"
Requires-Dist: pylint; extra == "test"
Requires-Dist: autopep8; extra == "test"
Requires-Dist: pre-commit; extra == "test"
Requires-Dist: hypothesis; extra == "test"
Requires-Dist: hypothesis-jsonschema; extra == "test"
Provides-Extra: mypy-types
Requires-Dist: lxml-stubs; extra == "mypy-types"
Requires-Dist: types-Pillow; extra == "mypy-types"
Requires-Dist: types-PyYAML; extra == "mypy-types"
Requires-Dist: types-Pygments; extra == "mypy-types"
Requires-Dist: types-colorama; extra == "mypy-types"
Requires-Dist: types-decorator; extra == "mypy-types"
Requires-Dist: types-docutils; extra == "mypy-types"
Requires-Dist: types-html5lib; extra == "mypy-types"
Requires-Dist: types-jsonschema; extra == "mypy-types"
Requires-Dist: types-psutil; extra == "mypy-types"
Requires-Dist: types-python-jose; extra == "mypy-types"
Requires-Dist: types-pytz; extra == "mypy-types"
Requires-Dist: types-redis; extra == "mypy-types"
Requires-Dist: types-requests; extra == "mypy-types"
Requires-Dist: types-setuptools; extra == "mypy-types"
Requires-Dist: types-six; extra == "mypy-types"
Requires-Dist: types-urllib3; extra == "mypy-types"
Provides-Extra: runners
Requires-Dist: toil[cwl]; extra == "runners"
Requires-Dist: cwl-utils; extra == "runners"
Provides-Extra: doc
Requires-Dist: sphinx; extra == "doc"
Requires-Dist: myst-parser; extra == "doc"
Requires-Dist: sphinx-autodoc-typehints; extra == "doc"
Provides-Extra: plots
Requires-Dist: matplotlib; extra == "plots"
Provides-Extra: cyto
Requires-Dist: ipycytoscape; extra == "cyto"
Provides-Extra: all-except-runner-src
Requires-Dist: sophios[cyto,doc,mypy-types,plots,test]; extra == "all-except-runner-src"
